tsbb15_labs/__init__.py
tsbb15_labs/lab1.py
tsbb15_labs/lab2.py
tsbb15_labs/lab3.py
tsbb15_labs/lab4.py
tsbb15_labs/images/boat.png
tsbb15_labs/images/cameraman.tif
tsbb15_labs/images/cornertest.png
tsbb15_labs/images/mystery_vector.mat
tsbb15_labs/images/mystery_vector.npy
tsbb15_labs/images/chessboard/img1.png
tsbb15_labs/images/chessboard/img10.png
tsbb15_labs/images/chessboard/img2.png
tsbb15_labs/images/chessboard/img3.png
tsbb15_labs/images/chessboard/img4.png
tsbb15_labs/images/chessboard/img5.png
tsbb15_labs/images/chessboard/img6.png
tsbb15_labs/images/chessboard/img7.png
tsbb15_labs/images/chessboard/img8.png
tsbb15_labs/images/chessboard/img9.png
tsbb15_labs/images/lab3/img1.png
tsbb15_labs/images/lab3/img2.png
tsbb15_labs/images/lab3/indoors05.png
tsbb15_labs/images/lab3/indoors06.png
tsbb15_labs-0.0.8.dist-info/METADATA
tsbb15_labs-0.0.8.dist-info/WHEEL
tsbb15_labs-0.0.8.dist-info/top_level.txt
tsbb15_labs-0.0.8.dist-info/RECORD
