Metadata-Version: 2.1
Name: tsbb15-labs
Version: 0.0.8
Summary: Convenience functions for the tsbb15 labs.
Home-page: https://github.com/Parskatt/tsbb15_labs
Author: Johan Edstedt
Author-email: johan.edstedt@liu.se
License: UNKNOWN
Platform: UNKNOWN
Classifier: Programming Language :: Python :: 3
Classifier: License :: OSI Approved :: MIT License
Classifier: Operating System :: OS Independent
Requires-Python: >=3.6
Requires-Dist: numpy
Requires-Dist: pillow
Requires-Dist: scipy
Requires-Dist: matplotlib
Requires-Dist: opencv-python
